progrock.py
progrock-0.3.1.dist-info/DESCRIPTION.rst
progrock-0.3.1.dist-info/METADATA
progrock-0.3.1.dist-info/metadata.json
progrock-0.3.1.dist-info/RECORD
progrock-0.3.1.dist-info/top_level.txt
progrock-0.3.1.dist-info/WHEEL
