Metadata-Version: 2.0
Name: progrock
Version: 0.3.1
Summary: A multi-progressbar implementation to complement multiprocessing.Process
Home-page: http://progrock.readthedocs.org
Author: Gavin M. Roy
Author-email: gavinmroy@gmail.com
License: Copyright (c) 2014 Gavin M. Roy
